env.py
envu-1.2.0.dist-info/LICENSE
envu-1.2.0.dist-info/METADATA
envu-1.2.0.dist-info/WHEEL
envu-1.2.0.dist-info/RECORD
