Metadata-Version: 2.3
Name: envu
Version: 1.2.0
Summary: The simplest possible syntax for loading environment variables from the .env file and system environment variables.
License: MIT
Keywords: env,.env,environment,environment variables
Author: Mohammad Hashem Nowruzi
Author-email: hashem.nowruzi@outlook.com
Maintainer: Mohammad Hashem Nowruzi
Maintainer-email: hashem.nowruzi@outlook.com
Requires-Python: >=3.8,<4.0
Classifier: Development Status :: 5 - Production/Stable
Classifier: Framework :: Django
Classifier: Framework :: Flask
Classifier: Intended Audience :: Developers
Classifier: License :: OSI Approved :: MIT License
Classifier: Natural Language :: English
Classifier: Operating System :: OS Independent
Classifier: Programming Language :: Python
Classifier: Programming Language :: Python :: 3
Classifier: Programming Language :: Python :: 3.8
Classifier: Programming Language :: Python :: 3.9
Classifier: Programming Language :: Python :: 3.10
Classifier: Programming Language :: Python :: 3.11
Classifier: Programming Language :: Python :: 3.12
Classifier: Programming Language :: Python :: 3.13
Classifier: Topic :: Software Development :: Libraries
Project-URL: Bug Tracker, https://github.com/hashem-nowruzi/envu/issues
Project-URL: Homepage, https://github.com/hashem-nowruzi/envu
Project-URL: Repository, https://github.com/hashem-nowruzi/envu
